ati18n/__init__.py
ati18n/cli.py
ati18n/ati18n/__init__.py
ati18n/ati18n/ati18n.py
ati18n/ati18n/aticheck.py
ati18n/ati18n/check_functions.py
ati18n/ati18n/common.py
ati18n/ati18n/config_utils.py
ati18n/ati18n/constants.py
ati18n/ati18n/state_backend.py
ati18n/ati18n/utils.py
ati18n-0.3.4.dist-info/LICENSE
ati18n-0.3.4.dist-info/METADATA
ati18n-0.3.4.dist-info/WHEEL
ati18n-0.3.4.dist-info/entry_points.txt
ati18n-0.3.4.dist-info/top_level.txt
ati18n-0.3.4.dist-info/RECORD
