Metadata-Version: 2.1
Name: ati18n
Version: 0.3.4
Summary: Python Boilerplate contains all the boilerplate you need to create a Python package.
Home-page: https://github.com/renweibo/ati18n
Author: Weibo Ren
Author-email: renweibo@gmail.com
License: MIT license
Keywords: ati18n
Platform: UNKNOWN
Classifier: Development Status :: 2 - Pre-Alpha
Classifier: Intended Audience :: Developers
Classifier: License :: OSI Approved :: MIT License
Classifier: Natural Language :: English
Classifier: Programming Language :: Python :: 3
Classifier: Programming Language :: Python :: 3.6
Classifier: Programming Language :: Python :: 3.7
Classifier: Programming Language :: Python :: 3.8
Requires-Python: >=3.6
Requires-Dist: Click
Requires-Dist: typer
